{"cameraMode":{"drawMode":0,"name":"Shaded","section":"Shading Mode"},"sceneLighting":false,"audioPlay":false,"sceneViewState":{"m_AlwaysRefresh":false,"showFog":true,"showSkybox":false,"showFlares":true,"showImageEffects":true,"showParticleSystems":true,"showVisualEffectGraphs":true,"m_FxEnabled":true},"in2DMode":false,"pivot":{"x":394.3143615722656,"y":453.42767333984377,"z":-66.04298400878906},"rotation":{"x":-0.017994891852140428,"y":0.021291345357894899,"z":-0.0003831289359368384,"w":-0.9996145963668823},"size":0.2835928797721863,"orthographic":false}